zd_feishu_excel/__init__.py
zd_feishu_excel/app.py
zd_feishu_excel/cell.py
zd_feishu_excel/consts.py
zd_feishu_excel/tests.py
zd_feishu_excel/utils.py
zd_feishu_excel/workbook.py
zd_feishu_excel-1.0.4.dist-info/LICENSE.txt
zd_feishu_excel-1.0.4.dist-info/METADATA
zd_feishu_excel-1.0.4.dist-info/WHEEL
zd_feishu_excel-1.0.4.dist-info/top_level.txt
zd_feishu_excel-1.0.4.dist-info/RECORD
