Metadata-Version: 2.1
Name: zd-feishu-excel
Version: 1.0.4
Summary: My short description for my project.
Home-page: https://github.com/me/myproject
Author: zhidonglv
Author-email: 2907872121@qq.com
License: MIT
Classifier: License :: OSI Approved :: MIT License
Classifier: Programming Language :: Python
Classifier: Programming Language :: Python :: 3
Classifier: Programming Language :: Python :: 3.6
Classifier: Programming Language :: Python :: Implementation :: CPython
Classifier: Programming Language :: Python :: Implementation :: PyPy
Requires-Python: >=3.6.0
License-File: LICENSE.txt
Requires-Dist: requests
